[{"name":"Xiayiqian","password":"123456","roles":[{"name":"manager"},{"name":"marketing"}]},{"name":"ren2","password":"incongruous","roles":[{"name":"marketing"}]},{"name":"ren1","password":"77777","roles":[{"name":"manager"},{"name":"marketing"}]},{"name":"Rui","password":"incongruous","roles":[{"name":"marketing"}]},{"name":"iii","password":"123456","roles":[{"name":"admin"}]},{"name":"Xiaodan1","password":"test","roles":[{"name":"marketing"}]},{"name":"Admin","password":"incongruous","roles":[{"name":"admin"}]},{"name":"Yiqian","password":"incongruous","roles":[{"name":"marketing"}]},{"name":"Xiaodan","password":"test","roles":[{"name":"marketing"}]}]